fun_with_py/__init__.py
fun_with_py/number.py
fun_with_py/strings.py
fun_with_py-1.8.0.dist-info/LICENCE.txt
fun_with_py-1.8.0.dist-info/METADATA
fun_with_py-1.8.0.dist-info/WHEEL
fun_with_py-1.8.0.dist-info/top_level.txt
fun_with_py-1.8.0.dist-info/RECORD
