Metadata-Version: 2.1
Name: fun-with-py
Version: 1.8.0
Summary: Strings and numbers
Home-page: UNKNOWN
Author: HSD
Author-email: <ashuhemantsingh@gmail.com>
License: UNKNOWN
Keywords: python,vowels,consonants,count
Platform: UNKNOWN
Classifier: Development Status :: 1 - Planning
Classifier: Intended Audience :: Developers
Classifier: Programming Language :: Python :: 3
Classifier: Operating System :: Unix
Classifier: Operating System :: MacOS :: MacOS X
Classifier: Operating System :: Microsoft :: Windows
License-File: LICENCE.txt
